complementaryc/__init__.py
complementaryc/bin/__init__.py
complementaryc/bin/complementary-strand
complementaryc/bin/complementary.so
complementaryc/bin/dummy_binary.exe
complementaryc/bin/dummy_binary.linux
complementaryc/bin/dummy_binary.mac
complementaryc/bin/osSelect.py
complementaryc/complement/__init__.py
complementaryc/complement/complementaryStrand.py
complementaryc/theYear/__init__.py
complementaryc/theYear/currentYear.py
complementaryc-1.0.1.dist-info/METADATA
complementaryc-1.0.1.dist-info/WHEEL
complementaryc-1.0.1.dist-info/top_level.txt
complementaryc-1.0.1.dist-info/RECORD
