Metadata-Version: 2.1
Name: complementaryc
Version: 1.0.1
Summary: AA small example package for complementary DNA conversion and telling the year
Home-page: https://bitbucket.org/agdiaz/bioinformatics-101
Author: Bio2Byte
Author-email: jose.gavalda.garcia@vub.be
License: UNKNOWN
Project-URL: Bug Tracker, https://bitbucket.org/agdiaz/bioinformatics-101/issues
Platform: UNKNOWN
Classifier: Programming Language :: Python :: 3
Classifier: Operating System :: OS Independent
Requires-Python: >=3.6
